qcgpu/__init__.py
qcgpu/backend.py
qcgpu/gate.py
qcgpu/state.py
qcgpu-0.1.1.dist-info/LICENSE
qcgpu-0.1.1.dist-info/METADATA
qcgpu-0.1.1.dist-info/WHEEL
qcgpu-0.1.1.dist-info/top_level.txt
qcgpu-0.1.1.dist-info/RECORD
