Metadata-Version: 2.1
Name: qcgpu
Version: 0.1.1
Summary: An OpenCL based quantum computer simulator
Home-page: https://github.com/qcgpu/qcgpu
Author: Adam Kelly
Author-email: adamkelly2201@gmail.com
License: UNKNOWN
Platform: UNKNOWN
Classifier: Programming Language :: Python :: 3
Classifier: License :: OSI Approved :: MIT License
Classifier: Operating System :: OS Independent
Requires-Dist: mako
Requires-Dist: pyopencl
Requires-Dist: pybind11
Requires-Dist: numpy
